cm_abtf/__init__.py
cm_abtf-0.0.0.2.dist-info/LICENSE
cm_abtf-0.0.0.2.dist-info/METADATA
cm_abtf-0.0.0.2.dist-info/WHEEL
cm_abtf-0.0.0.2.dist-info/top_level.txt
cm_abtf-0.0.0.2.dist-info/RECORD
