Metadata-Version: 2.1
Name: cm-abtf
Version: 0.0.0.2
Summary: TBD
License: Apache Software License (Apache 2.0)
Project-URL: Homepage, https://github.com/mlcommons/cm4abtf
Project-URL: Source, https://github.com/mlcommons/cm4abtf
Keywords: cmind,cm_abtf,cm4abtf,automation,portability,modularity,cknowledge,ctuning,mlcommons,mlperf,abtf
Classifier: Intended Audience :: Developers
Classifier: Intended Audience :: End Users/Desktop
Classifier: Intended Audience :: Science/Research
Classifier: Intended Audience :: Information Technology
Classifier: Topic :: Software Development
Classifier: Topic :: System
Classifier: Topic :: Scientific/Engineering
Classifier: License :: OSI Approved :: Apache Software License
Classifier: Operating System :: OS Independent
Classifier: Programming Language :: Python :: 3.8
Classifier: Programming Language :: Python :: 3.9
Classifier: Programming Language :: Python :: 3.10
Classifier: Programming Language :: Python :: 3.11
Classifier: Programming Language :: Python :: 3.12
Requires-Python: >=3.8
License-File: LICENSE
Requires-Dist: pyyaml
Requires-Dist: requests
Requires-Dist: setuptools
Requires-Dist: cmind
